odoo/addons/calendar_events_limit_user_attendance/README.rst
odoo/addons/calendar_events_limit_user_attendance/__init__.py
odoo/addons/calendar_events_limit_user_attendance/__manifest__.py
odoo/addons/calendar_events_limit_user_attendance/models/__init__.py
odoo/addons/calendar_events_limit_user_attendance/models/calendar_event.py
odoo/addons/calendar_events_limit_user_attendance/views/calendar_event.xml
odoo12_addon_calendar_events_limit_user_attendance-12.0.1.0.1.dist-info/METADATA
odoo12_addon_calendar_events_limit_user_attendance-12.0.1.0.1.dist-info/WHEEL
odoo12_addon_calendar_events_limit_user_attendance-12.0.1.0.1.dist-info/top_level.txt
odoo12_addon_calendar_events_limit_user_attendance-12.0.1.0.1.dist-info/RECORD
