Metadata-Version: 2.1
Name: odoo12-addon-calendar-events-limit-user-attendance
Version: 12.0.1.0.1
Summary: Limit attendance from calendar events to partners belonguing to users instead of any partner.
Home-page: https://coopdevs.org
Author: Coopdevs Treball SCCL
License: AGPL-3
Platform: UNKNOWN
Classifier: Programming Language :: Python
Classifier: Framework :: Odoo
Classifier: Framework :: Odoo :: 12.0
Classifier: License :: OSI Approved :: GNU Affero General Public License v3
Requires-Python: >=3.5
Requires-Dist: odoo <12.1dev,>=12.0a
